{
  "servers": {
    "dev": {
      "base": "serverpilot@xxx.xxx.xxx.xx:apps/{APPNAME}/public/",
      "assets": "serverpilot@xxx.xxx.xxx.xx:apps/{APPNAME}/public/wp-content/themes/{THEMENAME}/dist",
      "plugins": "serverpilot@xxx.xxx.xxx.xx:apps/{APPNAME}/public/wp-content/plugins/",
      "uploads": "serverpilot@xxx.xxx.xxx.xx:apps/{APPNAME}/public/wp-content/uploads/"      
    },
    "staging": {
      "base": "serverpilot@xxx.xxx.xxx.xx:apps/{APPNAME}/public/",
      "assets": "serverpilot@xxx.xxx.xxx.xx:apps/{APPNAME}/public/wp-content/themes/{THEMENAME}/dist",
      "plugins": "serverpilot@xxx.xxx.xxx.xx:apps/{APPNAME}/public/wp-content/plugins/",
      "uploads": "serverpilot@xxx.xxx.xxx.xx:apps/{APPNAME}/public/wp-content/uploads/"      
    },
    "prod": {
      "base": "serverpilot@xxx.xxx.xxx.xx:apps/{APPNAME}/public/",
      "assets": "serverpilot@xxx.xxx.xxx.xx:apps/{APPNAME}/public/wp-content/themes/{THEMENAME}/dist",
      "plugins": "serverpilot@xxx.xxx.xxx.xx:apps/{APPNAME}/public/wp-content/plugins/",
      "uploads": "serverpilot@xxx.xxx.xxx.xx:apps/{APPNAME}/public/wp-content/uploads/"      
    }      
  }
}
